{
  "stats": {
    "tconstruct:binding": {},
    "tconstruct:grip": {
      "accuracy": 0.0,
      "durability": 1.05,
      "melee_damage": 1.5
    },
    "tconstruct:handle": {
      "durability": 0.05,
      "melee_damage": 0.0,
      "melee_speed": 0.0,
      "mining_speed": 0.0
    },
    "tconstruct:head": {
      "durability": 400,
      "melee_attack": 1.5,
      "mining_speed": 5.2,
      "mining_tier": "minecraft:iron"
    },
    "tconstruct:limb": {
      "accuracy": 0.14,
      "draw_speed": -0.25,
      "durability": 400,
      "velocity": 0.15
    }
  }
}